{
  "AbstractHTML": "<span class=\"pkgname\">LinearAlgebraForCAP</span> provides a skeletal model of the category of finite dimensional vector spaces over a computable field.",
  "ArchiveFormats": ".tar.gz .zip",
  "ArchiveSHA256": "00a5979a751bd9afc19203fd4263b4ddc93e54270f8dca1e2659f1db17a45ab1",
  "ArchiveURL": "https://github.com/homalg-project/CAP_project/releases/download/LinearAlgebraForCAP-2025.09-01/LinearAlgebraForCAP-2025.09-01",
  "AvailabilityTest": null,
  "Date": "2025-09-17",
  "Dependencies": {
    "ExternalConditions": [],
    "GAP": ">= 4.13.0",
    "NeededOtherPackages": [
      [
        "ToolsForHomalg",
        ">= 2015.09.18"
      ],
      [
        "MatricesForHomalg",
        ">= 2023.01-01"
      ],
      [
        "GaussForHomalg",
        ">= 2021.04-02"
      ],
      [
        "CAP",
        ">= 2025.06-05"
      ],
      [
        "MonoidalCategories",
        ">= 2025.08-01"
      ]
    ]
  },
  "Extensions": [
    {
      "filename": "gap/MatrixCategory_as_CategoryOfRows.gi",
      "needed": [
        [
          "AdditiveClosuresForCAP",
          ">= 2025.06-01"
        ]
      ]
    }
  ],
  "IssueTrackerURL": "https://github.com/homalg-project/CAP_project/issues",
  "License": "GPL-2.0-or-later",
  "PackageDoc": [
    {
      "ArchiveURLSubset": [
        "doc"
      ],
      "BookName": "LinearAlgebraForCAP",
      "HTMLStart": "doc/chap0.html",
      "LongTitle": "Category of Matrices over a Field for CAP",
      "PDFFile": "doc/manual.pdf",
      "SixFile": "doc/manual.six"
    }
  ],
  "PackageInfoSHA256": "56717ff39f2c59d535e188db80c86e021be1bd572b45fdd9cc769a9778b892c1",
  "PackageInfoURL": "https://homalg-project.github.io/CAP_project/LinearAlgebraForCAP/PackageInfo.g",
  "PackageName": "LinearAlgebraForCAP",
  "PackageWWWHome": "https://homalg-project.github.io/pkg/LinearAlgebraForCAP",
  "Persons": [
    {
      "Email": "sebastian.gutsche@gmail.com",
      "FirstNames": "Sebastian",
      "Institution": "University of Siegen",
      "IsAuthor": true,
      "IsMaintainer": true,
      "LastName": "Gutsche",
      "Place": "Siegen",
      "PostalAddress": "Department Mathematik\nUniversität Siegen\nWalter-Flex-Straße 3\n57068 Siegen\nGermany",
      "WWWHome": "https://sebasguts.github.io/"
    },
    {
      "Email": "sebastian.posur@uni-muenster.de",
      "FirstNames": "Sebastian",
      "Institution": "University of Siegen",
      "IsAuthor": true,
      "IsMaintainer": true,
      "LastName": "Posur",
      "Place": "Siegen",
      "PostalAddress": "Department Mathematik\nUniversität Siegen\nWalter-Flex-Straße 3\n57068 Siegen\nGermany",
      "WWWHome": "https://sebastianpos.github.io"
    },
    {
      "Email": "f.zickgraf@dashdos.com",
      "FirstNames": "Fabian",
      "Institution": "University of Siegen",
      "IsAuthor": true,
      "IsMaintainer": true,
      "LastName": "Zickgraf",
      "Place": "Siegen",
      "PostalAddress": "Walter-Flex-Str. 3\n57068 Siegen\nGermany",
      "WWWHome": "https://github.com/zickgraf/"
    }
  ],
  "README_URL": "https://homalg-project.github.io/CAP_project/LinearAlgebraForCAP/README.md",
  "SourceRepository": {
    "Type": "git",
    "URL": "https://github.com/homalg-project/CAP_project"
  },
  "Status": "deposited",
  "Subtitle": "Category of Matrices over a Field for CAP",
  "TestFile": "tst/testall.g",
  "Version": "2025.09-01"
}
