{
  "AbstractHTML": "<span class=\"pkgname\">LinearAlgebraForCAP</span> provides a skeletal model of the category of finite dimensional vector spaces over a computable field.",
  "ArchiveFormats": ".tar.gz .zip",
  "ArchiveSHA256": "dac7749ad04cae8f1a1cbcada442ae0cc682eac99be50375f418362be602e971",
  "ArchiveURL": "https://github.com/homalg-project/CAP_project/releases/download/LinearAlgebraForCAP-2022.03-05/LinearAlgebraForCAP-2022.03-05",
  "AvailabilityTest": null,
  "Date": "01/04/2022",
  "Dependencies": {
    "ExternalConditions": [],
    "GAP": ">= 4.11.1",
    "NeededOtherPackages": [
      [
        "GAPDoc",
        ">= 1.5"
      ],
      [
        "ToolsForHomalg",
        ">=2015.09.18"
      ],
      [
        "MatricesForHomalg",
        ">= 2021.12-01"
      ],
      [
        "GaussForHomalg",
        ">= 2021.04-02"
      ],
      [
        "CAP",
        ">= 2022.01-05"
      ],
      [
        "MonoidalCategories",
        ">= 2021.12-11"
      ]
    ],
    "SuggestedOtherPackages": [
      [
        "FreydCategoriesForCAP",
        ">= 2021.12-02"
      ]
    ]
  },
  "IssueTrackerURL": "https://github.com/homalg-project/CAP_project/issues",
  "License": "GPL-2.0-or-later",
  "PackageDoc": [
    {
      "ArchiveURLSubset": [
        "doc"
      ],
      "BookName": "LinearAlgebraForCAP",
      "HTMLStart": "doc/chap0.html",
      "LongTitle": "Category of Matrices over a Field for CAP",
      "PDFFile": "doc/manual.pdf",
      "SixFile": "doc/manual.six"
    }
  ],
  "PackageInfoSHA256": "596e38a7748d6c0515bf5b13f269ec62361cb8f4e7d7abb7f035a67cf68ac8b0",
  "PackageInfoURL": "https://homalg-project.github.io/CAP_project/LinearAlgebraForCAP/PackageInfo.g",
  "PackageName": "LinearAlgebraForCAP",
  "PackageWWWHome": "https://homalg-project.github.io/pkg/LinearAlgebraForCAP",
  "Persons": [
    {
      "Email": "gutsche@mathematik.uni-siegen.de",
      "FirstNames": "Sebastian",
      "Institution": "University of Siegen",
      "IsAuthor": true,
      "IsMaintainer": true,
      "LastName": "Gutsche",
      "Place": "Siegen",
      "PostalAddress": "Department Mathematik\nUniversität Siegen\nWalter-Flex-Straße 3\n57068 Siegen\nGermany",
      "WWWHome": "https://sebasguts.github.io/"
    },
    {
      "Email": "sebastian.posur@uni-siegen.de",
      "FirstNames": "Sebastian",
      "Institution": "University of Siegen",
      "IsAuthor": true,
      "IsMaintainer": true,
      "LastName": "Posur",
      "Place": "Siegen",
      "PostalAddress": "Department Mathematik\nUniversität Siegen\nWalter-Flex-Straße 3\n57068 Siegen\nGermany",
      "WWWHome": "https://sebastianpos.github.io"
    }
  ],
  "README_URL": "https://homalg-project.github.io/CAP_project/LinearAlgebraForCAP/README.md",
  "SourceRepository": {
    "Type": "git",
    "URL": "https://github.com/homalg-project/CAP_project"
  },
  "Status": "deposited",
  "Subtitle": "Category of Matrices over a Field for CAP",
  "TestFile": "tst/testall.g",
  "Version": "2022.03-05"
}
