{
  "AbstractHTML": "The <span class=\"transgrp\">TransGrp</span> package provides the library of transitive groups.",
  "ArchiveFormats": ".tar.gz",
  "ArchiveSHA256": "6f2ec142a004f9d5e3b28bfa03246472fee93ceb12837206960bcb560eb72376",
  "ArchiveURL": "https://www.math.colostate.edu/~hulpke/transgrp/transgrp3.6.5",
  "AvailabilityTest": null,
  "Date": "15/12/2023",
  "Dependencies": {
    "ExternalConditions": [],
    "GAP": ">=4.9",
    "NeededOtherPackages": [],
    "SuggestedOtherPackages": []
  },
  "IssueTrackerURL": "https://github.com/hulpke/transgrp/issues",
  "Keywords": [
    "Transitive Groups Library"
  ],
  "License": "Artistic-2.0 AND (GPL-2.0-only OR GPL-3.0-only)",
  "PackageDoc": [
    {
      "ArchiveURLSubset": [
        "doc/manual.pdf",
        "htm"
      ],
      "Autoload": true,
      "BookName": "transgrp",
      "HTMLStart": "htm/chapters.htm",
      "LongTitle": "Transitive Groups Library",
      "PDFFile": "doc/manual.pdf",
      "SixFile": "doc/manual.six"
    }
  ],
  "PackageInfoSHA256": "283b13cce0ce92ea8b4d3668ef6e8e5404a892c75b16b8c7406f98bbf79ef423",
  "PackageInfoURL": "https://www.math.colostate.edu/~hulpke/transgrp/PackageInfo.g",
  "PackageName": "TransGrp",
  "PackageWWWHome": "https://www.math.colostate.edu/~hulpke/transgrp",
  "Persons": [
    {
      "Email": "hulpke@math.colostate.edu",
      "FirstNames": "Alexander",
      "Institution": "Department of Mathematics, Colorado State University",
      "IsAuthor": true,
      "IsMaintainer": true,
      "LastName": "Hulpke",
      "Place": "Fort Collins, CO",
      "WWWHome": "https://www.math.colostate.edu/~hulpke"
    }
  ],
  "README_URL": "https://www.math.colostate.edu/~hulpke/transgrp/README.txt",
  "SourceRepository": {
    "Type": "git",
    "URL": "https://github.com/hulpke/transgrp"
  },
  "Status": "deposited",
  "Subtitle": "Transitive Groups Library",
  "TestFile": "tst/testall.g",
  "Version": "3.6.5"
}
