{
  "AbstractHTML": "The <span class=\"pkgname\">SCO</span> package provides functionality to compute simplicial cohomology of orbifolds",
  "ArchiveFormats": ".tar.gz .zip",
  "ArchiveSHA256": "e7059a6a33cd200d98a423142611a1d09514ad414a958839fe5072389704cd4e",
  "ArchiveURL": "https://github.com/homalg-project/homalg_project/releases/download/SCO-2020.10-02/SCO-2020.10-02",
  "Autoload": false,
  "AvailabilityTest": null,
  "Date": "16/10/2020",
  "Dependencies": {
    "ExternalConditions": [],
    "GAP": ">=4.7",
    "NeededOtherPackages": [
      [
        "MatricesForHomalg",
        ">= 2011.08.10"
      ],
      [
        "Modules",
        ">= 2011.06.29"
      ],
      [
        "GAPDoc",
        ">= 1.0"
      ]
    ],
    "SuggestedOtherPackages": []
  },
  "IssueTrackerURL": "https://github.com/homalg-project/homalg_project/issues",
  "Keywords": [
    "homology",
    "cohomology",
    "orbifold",
    "groupoid",
    "simplicial",
    "triangulation"
  ],
  "License": "GPL-2.0-or-later",
  "PackageDoc": [
    {
      "ArchiveURLSubset": [
        "doc"
      ],
      "Autoload": true,
      "BookName": "SCO",
      "HTMLStart": "doc/chap0.html",
      "LongTitle": "SCO - Simplicial Cohomology of Orbifolds",
      "PDFFile": "doc/manual.pdf",
      "SixFile": "doc/manual.six"
    }
  ],
  "PackageInfoSHA256": "b9f1fed0e5e230fdcc2f38215bb08c90e36b76e5c931b1198005303327361f8d",
  "PackageInfoURL": "https://homalg-project.github.io/homalg_project/SCO/PackageInfo.g",
  "PackageName": "SCO",
  "PackageWWWHome": "https://homalg-project.github.io/homalg_project/SCO",
  "Persons": [
    {
      "Email": "simon.goertzen@rwth-aachen.de",
      "FirstNames": "Simon",
      "Institution": "RWTH Aachen University",
      "IsAuthor": true,
      "IsMaintainer": false,
      "LastName": "Görtzen",
      "Place": "Aachen",
      "PostalAddress": "Simon Görtzen\nLehrstuhl B fuer Mathematik, RWTH Aachen\nTemplergraben 64\n52062 Aachen\nGermany",
      "WWWHome": "https://www.linkedin.com/in/simongoertzen/"
    },
    {
      "Email": "mohamed.barakat@uni-siegen.de",
      "FirstNames": "Mohamed",
      "Institution": "University of Siegen",
      "IsAuthor": false,
      "IsMaintainer": true,
      "LastName": "Barakat",
      "Place": "Siegen",
      "PostalAddress": "Walter-Flex-Str. 3\n57072 Siegen\nGermany",
      "WWWHome": "https://mohamed-barakat.github.io"
    }
  ],
  "README_URL": "https://homalg-project.github.io/homalg_project/SCO/README.md",
  "SourceRepository": {
    "Type": "git",
    "URL": "https://github.com/homalg-project/homalg_project"
  },
  "Status": "deposited",
  "Subtitle": "SCO - Simplicial Cohomology of Orbifolds",
  "Version": "2020.10-02"
}
