{
  "AbstractHTML": "<span class=\"pkgname\">GRAPE</span> is a package for computing with graphs and groups, and is primarily designed for constructing and analysing graphs related to groups, finite geometries, and designs.",
  "AcceptDate": "07/1993",
  "ArchiveFormats": ".tar.gz",
  "ArchiveSHA256": "911b7e181161a4935b5c36cd370a11b250769735ea2f10087bbd75a8de3a2fa1",
  "ArchiveURL": "https://github.com/gap-packages/grape/releases/download/v4.9.3/grape-4.9.3",
  "AvailabilityTest": null,
  "CommunicatedBy": "Leonard Soicher (QMUL)",
  "Date": "06/09/2025",
  "Dependencies": {
    "ExternalConditions": [],
    "GAP": ">=4.11",
    "NeededOtherPackages": [],
    "SuggestedOtherPackages": []
  },
  "IssueTrackerURL": "https://github.com/gap-packages/grape/issues",
  "Keywords": [
    "graph",
    "design",
    "finite geometry",
    "clique number",
    "chromatic number"
  ],
  "License": "Apache-2.0 AND GPL-2.0-or-later",
  "PackageDoc": [
    {
      "ArchiveURLSubset": [
        "htm",
        "doc/manual.pdf"
      ],
      "BookName": "GRAPE",
      "HTMLStart": "htm/chapters.htm",
      "LongTitle": "GRaph Algorithms using PErmutation groups",
      "PDFFile": "doc/manual.pdf",
      "SixFile": "doc/manual.six"
    }
  ],
  "PackageInfoSHA256": "0758870ecc489b690592f510a3c94a1d86578137dbb0e695d1f911edbd584691",
  "PackageInfoURL": "https://gap-packages.github.io/grape/PackageInfo.g",
  "PackageName": "GRAPE",
  "PackageWWWHome": "https://gap-packages.github.io/grape",
  "Persons": [
    {
      "Email": "L.H.Soicher@qmul.ac.uk",
      "FirstNames": "Leonard H.",
      "Institution": "School of Mathematical Sciences, Queen Mary University of London",
      "IsAuthor": true,
      "IsMaintainer": true,
      "LastName": "Soicher",
      "Place": "London, UK",
      "WWWHome": "https://webspace.maths.qmul.ac.uk/l.h.soicher/"
    }
  ],
  "README_URL": "https://gap-packages.github.io/grape/README.md",
  "SourceRepository": {
    "Type": "git",
    "URL": "https://github.com/gap-packages/grape"
  },
  "Status": "accepted",
  "Subtitle": "GRaph Algorithms using PErmutation groups",
  "TestFile": "tst/testall.g",
  "Version": "4.9.3"
}
